<?xml version="1.0" encoding="UTF-8" standalone="yes"?>
<results athletes="7">
    <places id="1-2">
        <athlete name="John Smith" points="4202"/>
        <athlete name="Igor Zamyatin" points="4202"/>
    </places>
    <places id="3">
        <athlete name="Jaan Lepp" points="3497"/>
    </places>
    <places id="4-6">
        <athlete name="Bruno Gordo" points="3202"/>
        <athlete name="Jane Doe" points="3202"/>
        <athlete name="Travis Daye" points="3202"/>
    </places>
    <places id="7">
        <athlete name="Foo Bar" points="3101"/>
    </places>
</results>
